setup.py
opps/__init__.py
opps/liveblogging/__init__.py
opps/liveblogging/admin.py
opps/liveblogging/api.py
opps/liveblogging/conf.py
opps/liveblogging/forms.py
opps/liveblogging/models.py
opps/liveblogging/signals.py
opps/liveblogging/urls.py
opps/liveblogging/urls_api.py
opps/liveblogging/views.py
opps/liveblogging/migrations/0001_initial.py
opps/liveblogging/migrations/__init__.py
opps_liveblogging.egg-info/PKG-INFO
opps_liveblogging.egg-info/SOURCES.txt
opps_liveblogging.egg-info/dependency_links.txt
opps_liveblogging.egg-info/namespace_packages.txt
opps_liveblogging.egg-info/requires.txt
opps_liveblogging.egg-info/top_level.txt