Metadata-Version: 1.1
Name: opps-liveblogging
Version: 0.2.1
Summary: Liveblogging app, event broadcast via text
Home-page: UNKNOWN
Author: Thiago Avelino
Author-email: thiago@avelino.xxx
License: UNKNOWN
Keywords: Liveblogging app for opps cms broadcast event via text
Platform: UNKNOWN
Classifier: Development Status :: 4 - Beta
Classifier: Intended Audience :: Developers
Classifier: Operating System :: OS Independent
Classifier: Framework :: Opps
Classifier: Programming Language :: Python
Classifier: Programming Language :: Python :: 2.7
Classifier: Operating System :: OS Independent
Classifier: Topic :: Internet :: WWW/HTTP :: Dynamic Content
Classifier: Topic :: Software Development :: Libraries :: Python Modules
